spellcrafting/__init__.py
spellcrafting/_pydantic_ai.py
spellcrafting/_pyproject.py
spellcrafting/config.py
spellcrafting/exceptions.py
spellcrafting/guard.py
spellcrafting/logging.py
spellcrafting/media.py
spellcrafting/on_fail.py
spellcrafting/py.typed
spellcrafting/result.py
spellcrafting/spell.py
spellcrafting/validator.py
spellcrafting-0.1.1.dist-info/METADATA
spellcrafting-0.1.1.dist-info/WHEEL
spellcrafting-0.1.1.dist-info/RECORD
