Metadata-Version: 2.4
Name: spellcrafting
Version: 0.1.1
Summary: LLMs as a Python language feature
Project-URL: Homepage, https://github.com/sammcvicker/spellcrafting
Project-URL: Documentation, https://github.com/sammcvicker/spellcrafting
Project-URL: Repository, https://github.com/sammcvicker/spellcrafting
Author: Sam McVicker
License: MIT
Keywords: ai,anthropic,llm,openai,pydantic,structured-output
Classifier: Development Status :: 3 - Alpha
Classifier: Intended Audience :: Developers
Classifier: License :: OSI Approved :: MIT License
Classifier: Programming Language :: Python :: 3.10
Classifier: Programming Language :: Python :: 3.11
Classifier: Programming Language :: Python :: 3.12
Classifier: Programming Language :: Python :: 3.13
Classifier: Topic :: Scientific/Engineering :: Artificial Intelligence
Requires-Python: >=3.10
Requires-Dist: pydantic-ai<2.0.0,>=1.38.0
Requires-Dist: pydantic<3.0.0,>=2.0.0
Requires-Dist: tomli>=2.0.0; python_version < '3.11'
Provides-Extra: all
Requires-Dist: ddtrace>=2.0.0; extra == 'all'
Requires-Dist: logfire>=0.1.0; extra == 'all'
Requires-Dist: opentelemetry-api>=1.0.0; extra == 'all'
Requires-Dist: opentelemetry-sdk>=1.0.0; extra == 'all'
Requires-Dist: pillow>=9.0.0; extra == 'all'
Requires-Dist: python-dotenv>=1.0.0; extra == 'all'
Provides-Extra: datadog
Requires-Dist: ddtrace>=2.0.0; extra == 'datadog'
Provides-Extra: dotenv
Requires-Dist: python-dotenv>=1.0.0; extra == 'dotenv'
Provides-Extra: images
Requires-Dist: pillow>=9.0.0; extra == 'images'
Provides-Extra: logfire
Requires-Dist: logfire>=0.1.0; extra == 'logfire'
Provides-Extra: otel
Requires-Dist: opentelemetry-api>=1.0.0; extra == 'otel'
Requires-Dist: opentelemetry-sdk>=1.0.0; extra == 'otel'
